linger/__init__.py
linger/__main__.py
linger/linger.py
linger-1.0.1.dist-info/LICENSE
linger-1.0.1.dist-info/METADATA
linger-1.0.1.dist-info/WHEEL
linger-1.0.1.dist-info/entry_points.txt
linger-1.0.1.dist-info/top_level.txt
linger-1.0.1.dist-info/RECORD
