Metadata-Version: 2.1
Name: linger
Version: 1.0.1
Summary: Message queue and pubsub service with HTTP API
Home-page: https://github.com/nephics/linger
Author: Jacob Svensson
Author-email: jacob@nephics.com
License: http://www.apache.org/licenses/LICENSE-2.0
Platform: UNKNOWN
Classifier: Development Status :: 5 - Production/Stable
Classifier: Intended Audience :: Developers
Classifier: License :: OSI Approved :: Apache Software License
Classifier: Programming Language :: Python :: 3
Classifier: Topic :: System :: Distributed Computing
Classifier: Topic :: System :: Networking
Classifier: Topic :: Utilities
Requires-Dist: tornado (>=4.5.2)
